rflogs/__init__.py
rflogs-0.22.0.dist-info/LICENSE
rflogs-0.22.0.dist-info/METADATA
rflogs-0.22.0.dist-info/WHEEL
rflogs-0.22.0.dist-info/entry_points.txt
rflogs-0.22.0.dist-info/RECORD
