Metadata-Version: 2.1
Name: rflogs
Version: 0.22.0
Summary: A CLI tool for uploading Robot Framework test results to rflogs.io
License: Apache-2.0
Author: Mikko Korpela
Author-email: mikko.korpela@gmail.com
Requires-Python: >=3.8,<4.0
Classifier: License :: OSI Approved :: Apache Software License
Classifier: Programming Language :: Python :: 3
Classifier: Programming Language :: Python :: 3.8
Classifier: Programming Language :: Python :: 3.9
Classifier: Programming Language :: Python :: 3.10
Classifier: Programming Language :: Python :: 3.11
Classifier: Programming Language :: Python :: 3.12
Requires-Dist: requests (>=2.32.3,<3.0.0)
Requires-Dist: robotframework (>=6.0,<9.0)
